{
    "en": {
        "translation": {
            "giveaway": "Giveaway",
            "prize": "Prize:",
            "entries": "Entries",
            "joincommand": "(!join)",
            "winner_announce": "And the winner is...",
            "winner_instruction": "Type !win to claim your prize",
            "congrats": "Congrats",
            "item_won_announce": "You won",
            "bad_command": "Giveaway command must be in the form of !startgiv NumberOfMinutes Title"
        }
    },
    "cs": {
        "translation": {
            "giveaway": "Předání ceny",
            "prize": "Výhra:",
            "entries": "Záznamy",
            "joincommand": "(!join)",
            "winner_announce": "A vítězem je...",
            "winner_instruction": "Napište !win a vyzvedněte si svou cenu",
            "congrats": "Gratuluji",
            "item_won_announce": "Vyhráli jste",
            "bad_command": "Giveaway command must be in the form of !startgiv NumberOfMinutes Title"
        }
    },
    "de": {
        "credit": "@moertel",
        "translation": {
            "giveaway": "Gewinnspiel",
            "prize": "Preis:",
            "entries": "Einträge",
            "joincommand": "(!join)",
            "winner_announce": "Der/die Gewinner*in ist...",
            "winner_instruction": "Gib !win ein, um deinen Preis einzufordern",
            "congrats": "Herzlichen Glückwunsch",
            "item_won_announce": "Du hast gewonnen",
            "bad_command": "Giveaway command must be in the form of !startgiv NumberOfMinutes Title"
        }
    },
    "es": {
        "translation": {
            "giveaway": "Giveaway",
            "prize": "Premio:",
            "entries": "Entries",
            "joincommand": "(!join)",
            "winner_announce": "Y el ganador es...",
            "winner_instruction": "Escribe !win para reclamar tu premio",
            "congrats": "Congrats",
            "item_won_announce": "Has ganado",
            "bad_command": "Giveaway command must be in the form of !startgiv NumberOfMinutes Title"
        }
    },
    "fr": {
        "translation": {
            "giveaway": "Giveaway",
            "prize": "Prix:",
            "entries": "Entrées",
            "joincommand": "(!join)",
            "winner_announce": "Et le gagnant est...",
            "winner_instruction": "Tapez !win pour réclamer votre prix",
            "congrats": "Félicitations",
            "item_won_announce": "Vous avez gagné",
            "bad_command": "Giveaway command must be in the form of !startgiv NumberOfMinutes Title"
        }
    }
}
